pykosmos/__init__.py
pykosmos/apextract.py
pykosmos/flatfield.py
pykosmos/fluxcal.py
pykosmos/identify.py
pykosmos/imtools.py
pykosmos/kosmos_tools.py
pykosmos/wrappers.py
pykosmos/resources/arctemplates/ArBlue0.86-high.spec
pykosmos/resources/arctemplates/ArBlue1.18-ctr.spec
pykosmos/resources/arctemplates/ArBlue2.0-low.spec
pykosmos/resources/arctemplates/ArRed0.86-high.spec
pykosmos/resources/arctemplates/ArRed1.18-ctr.spec
pykosmos/resources/arctemplates/ArRed2.0-low.spec
pykosmos/resources/arctemplates/DIS_B400.spec
pykosmos/resources/arctemplates/DIS_R300.spec
pykosmos/resources/arctemplates/KrBlue0.86-high.spec
pykosmos/resources/arctemplates/KrBlue1.18-ctr.spec
pykosmos/resources/arctemplates/KrBlue2.0-low.spec
pykosmos/resources/arctemplates/KrRed0.86-high.spec
pykosmos/resources/arctemplates/KrRed1.18-ctr.spec
pykosmos/resources/arctemplates/KrRed2.0-low.spec
pykosmos/resources/arctemplates/NeBlue0.86-high.spec
pykosmos/resources/arctemplates/NeBlue1.18-ctr.spec
pykosmos/resources/arctemplates/NeBlue2.0-low.spec
pykosmos/resources/arctemplates/NeRed0.86-high.spec
pykosmos/resources/arctemplates/NeRed1.18-ctr.spec
pykosmos/resources/arctemplates/NeRed2.0-low.spec
pykosmos/resources/arctemplates/README.md
pykosmos/resources/extinction/apoextinct.dat
pykosmos/resources/extinction/ctioextinct.dat
pykosmos/resources/extinction/kpnoextinct.dat
pykosmos/resources/extinction/ormextinct.dat
pykosmos/resources/linelists/README
pykosmos/resources/linelists/apohenear.dat
pykosmos/resources/linelists/argon.dat
pykosmos/resources/linelists/ctiohear.dat
pykosmos/resources/linelists/ctiohenear.dat
pykosmos/resources/linelists/cuar.dat
pykosmos/resources/linelists/fear.dat
pykosmos/resources/linelists/henear.dat
pykosmos/resources/linelists/henearhres.dat
pykosmos/resources/linelists/idhenear.dat
pykosmos/resources/linelists/idhenearT.dat
pykosmos/resources/linelists/krypton.dat
pykosmos/resources/linelists/lowskylines.dat
pykosmos/resources/linelists/ohlines.dat
pykosmos-0.3.8.1.dist-info/METADATA
pykosmos-0.3.8.1.dist-info/WHEEL
pykosmos-0.3.8.1.dist-info/licenses/LICENSE
pykosmos-0.3.8.1.dist-info/RECORD
