Metadata-Version: 2.3
Name: pykosmos
Version: 0.3.8.1
Summary: A spectral data reduction pipeline
Project-URL: Homepage, https://github.com/jradavenport/pykosmos
Project-URL: Issues, https://github.com/jradavenport/pykosmos/issues
Author-email: James Davenport <jrad@uw.edu>
License-File: LICENSE
Classifier: License :: OSI Approved :: MIT License
Classifier: Operating System :: OS Independent
Classifier: Programming Language :: Python :: 3
Requires-Python: >=3.8
Requires-Dist: astropy>=5.3
Requires-Dist: ccdproc>=2.4.1
Requires-Dist: dtw-python>=1.3
Requires-Dist: george>0.4
Requires-Dist: ipympl
Requires-Dist: ipywidgets
Requires-Dist: matplotlib>=3.5
Requires-Dist: numpy>=1.21
Requires-Dist: pandas
Requires-Dist: scipy
Requires-Dist: specreduce>=1.4.0
Requires-Dist: specutils>=1.12.0
